mypackage/__init__.py
mypackage/main.py
autoinstaller_backendpk-0.0.1.dist-info/LICENSE
autoinstaller_backendpk-0.0.1.dist-info/METADATA
autoinstaller_backendpk-0.0.1.dist-info/WHEEL
autoinstaller_backendpk-0.0.1.dist-info/top_level.txt
autoinstaller_backendpk-0.0.1.dist-info/RECORD
